fillet/__init__.py
fillet/add_device.py
fillet/core.py
fillet/main.py
fillet/simulation.py
fillet/version.py
fillet-0.0.3.dist-info/LICENSE
fillet-0.0.3.dist-info/METADATA
fillet-0.0.3.dist-info/WHEEL
fillet-0.0.3.dist-info/entry_points.txt
fillet-0.0.3.dist-info/top_level.txt
fillet-0.0.3.dist-info/RECORD
