Metadata-Version: 2.1
Name: fillet
Version: 0.0.3
Summary: Assistance scripts for ONT MinKNOW
Home-page: https://github.com/alexomics/fillet
Author: Alexander Payne
Author-email: alexander.payne@nottingham.ac.uk
License: UNKNOWN
Platform: UNKNOWN
Classifier: Programming Language :: Python :: 3
Classifier: License :: OSI Approved :: GNU General Public License v3 (GPLv3)
Classifier: Operating System :: OS Independent
Requires-Python: >=3.5
Requires-Dist: toml
